configparser_override/__init__.py
configparser_override/_override_strategy.py
configparser_override/_strategy_factory.py
configparser_override/configparser_override.py
configparser_override/convert.py
configparser_override/exceptions.py
configparser_override/file_collector.py
configparser_override/py.typed
configparser_override/types.py
configparser_override-0.11.0.dist-info/LICENSE
configparser_override-0.11.0.dist-info/METADATA
configparser_override-0.11.0.dist-info/WHEEL
configparser_override-0.11.0.dist-info/top_level.txt
configparser_override-0.11.0.dist-info/RECORD
