Metadata-Version: 2.1
Name: configparser-override
Version: 0.11.0
Summary: ConfigParser with environment variable and direct assignment overrides
Author: Richard Nordström
Project-URL: Repository, https://github.com/RicNord/configparser-override.git
Project-URL: Issues, https://github.com/RicNord/configparser-override/issues
Keywords: cfg,conf,configparser,configuration,ini,override,parsing
Classifier: Intended Audience :: Developers
Classifier: Programming Language :: Python :: 3
Classifier: License :: OSI Approved :: MIT License
License-File: LICENSE
Provides-Extra: dev
Requires-Dist: bandit[toml] ; extra == 'dev'
Requires-Dist: build ; extra == 'dev'
Requires-Dist: bump-my-version ; extra == 'dev'
Requires-Dist: mypy ; extra == 'dev'
Requires-Dist: pre-commit ; extra == 'dev'
Requires-Dist: pytest ; extra == 'dev'
Requires-Dist: pytest-cov ; extra == 'dev'
Requires-Dist: ruff ; extra == 'dev'
Provides-Extra: docs
Requires-Dist: myst-parser ; extra == 'docs'
Requires-Dist: sphinx ; extra == 'docs'
Requires-Dist: sphinx-autobuild ; extra == 'docs'
Requires-Dist: sphinx-rtd-theme ; extra == 'docs'
Provides-Extra: style
Requires-Dist: ruff ; extra == 'style'
